Workbook

Sheet données
B1: tweet_id | C1: text | D1: science_related | E1: scientific_claim | F1: scientific_reference | G1: scientific_context | I1: =_xlfn.CONCAT("chevauchant ",E1) -> chevauchant scientific_claim | J1: =_xlfn.CONCAT("chevauchant ",F1) -> chevauchant scientific_reference | K1: =_xlfn.CONCAT("chevauchant ",G1) -> chevauchant scientific_context
A2: 0 | B2: 3.1667e+17 | C2: Knees are a bit sore. i guess that's a sign that my recent treadmilling is working | D2: 0 | E2: 0.0 | F2: 0.0 | G2: 0.0 | I2: =AND($E2="1.0", OR($F2="1.0",$G2="1.0")) -> FALSE | J2: =AND($F2="1.0", OR($E2="1.0",$G2="1.0")) -> FALSE | K2: =AND($G2="1.0", OR($F2="1.0",$E2="1.0")) -> FALSE
A3: 1 | B3: 3.1909087e+17 | C3: McDonald's breakfast stop then the gym 🏀💪 | D3: 0 | E3: 0.0 | F3: 0.0 | G3: 0.0 | I3: =AND($E3="1.0", OR($F3="1.0",$G3="1.0")) -> FALSE | J3: =AND($F3="1.0", OR($E3="1.0",$G3="1.0")) -> FALSE | K3: =AND($G3="1.0", OR($F3="1.0",$E3="1.0")) -> FALSE
A4: 2 | B4: 3.2203093e+17 | C4: Can any Gynecologist with Cancer Experience explain the dangers of Transvaginal Douching with Fluoride or other toxins such as Dioxin? #PDX | D4: 1 | E4: 1.0 | F4: 0.0 | G4: 0.0 | I4: =AND($E4="1.0", OR($F4="1.0",$G4="1.0")) -> FALSE | J4: =AND($F4="1.0", OR($E4="1.0",$G4="1.0")) -> FALSE | K4: =AND($G4="1.0", OR($F4="1.0",$E4="1.0")) -> FALSE
A5: 3 | B5: 3.2269483e+17 | C5: Couch-lock highs lead to sleeping in the couch. Gotta stop doing this shit. | D5: 1 | E5: 1.0 | F5: 0.0 | G5: 0.0 | I5: =AND($E5="1.0", OR($F5="1.0",$G5="1.0")) -> FALSE | J5: =AND($F5="1.0", OR($E5="1.0",$G5="1.0")) -> FALSE | K5: =AND($G5="1.0", OR($F5="1.0",$E5="1.0")) -> FALSE
A6: 4 | B6: 3.2852443e+17 | C6: Does daily routine help prevent problems with bipolar disorder http://t.co/XGUfUDoLJB | D6: 1 | E6: 1.0 | F6: 0.0 | G6: 0.0 | I6: =AND($E6="1.0", OR($F6="1.0",$G6="1.0")) -> FALSE | J6: =AND($F6="1.0", OR($E6="1.0",$G6="1.0")) -> FALSE | K6: =AND($G6="1.0", OR($F6="1.0",$E6="1.0")) -> FALSE
A7: 6 | B7: 3.313962e+17 | C7: The Impact of Infertility on You and Your Relationship http://t.co/7pF7Z0wH8f | D7: 0 | E7: 0.0 | F7: 0.0 | G7: 0.0 | I7: =AND($E7="1.0", OR($F7="1.0",$G7="1.0")) -> FALSE | J7: =AND($F7="1.0", OR($E7="1.0",$G7="1.0")) -> FALSE | K7: =AND($G7="1.0", OR($F7="1.0",$E7="1.0")) -> FALSE
A8: 8 | B8: 3.3326679e+17 | C8: “Traffic Jam” In Brain’s Neurons Could Be Cause Of Statin-Related Cognitive Decline http://t.co/kQ3XPdePKX | D8: 1 | E8: 1.0 | F8: 1.0 | G8: 1.0 | I8: =AND($E8="1.0", OR($F8="1.0",$G8="1.0")) -> TRUE | J8: =AND($F8="1.0", OR($E8="1.0",$G8="1.0")) -> TRUE | K8: =AND($G8="1.0", OR($F8="1.0",$E8="1.0")) -> TRUE
A9: 9 | B9: 3.3428273e+17 | C9: Can playing more games improve lives and save the world? by @chris_pelle via @PostArcade http://t.co/uEtVu099Ad #CDA30 | D9: 1 | E9: 1.0 | F9: 0.0 | G9: 0.0 | I9: =AND($E9="1.0", OR($F9="1.0",$G9="1.0")) -> FALSE | J9: =AND($F9="1.0", OR($E9="1.0",$G9="1.0")) -> FALSE | K9: =AND($G9="1.0", OR($F9="1.0",$E9="1.0")) -> FALSE
A10: 10 | B10: 3.3435004e+17 | C10: The effect of climate change on iceberg production by Greenland glaciers http://t.co/CtnPhcmD7c | D10: 1 | E10: 0.0 | F10: 1.0 | G10: 1.0 | I10: =AND($E10="1.0", OR($F10="1.0",$G10="1.0")) -> FALSE | J10: =AND($F10="1.0", OR($E10="1.0",$G10="1.0")) -> TRUE | K10: =AND($G10="1.0", OR($F10="1.0",$E10="1.0")) -> TRUE
A11: 11 | B11: 3.3554224e+17 | C11: @HankAzaria @TheSimpsons oh loneliness and cheeseburgers are a dangerous mix | D11: 0 | E11: 0.0 | F11: 0.0 | G11: 0.0 | I11: =AND($E11="1.0", OR($F11="1.0",$G11="1.0")) -> FALSE | J11: =AND($F11="1.0", OR($E11="1.0",$G11="1.0")) -> FALSE | K11: =AND($G11="1.0", OR($F11="1.0",$E11="1.0")) -> FALSE
A12: 12 | B12: 3.3643179e+17 | C12: #bbcsportsday Honestly think Liverpool are a left back and a right wing away from CL. Fabio Coentrao and James Rodriguez? | D12: 0 | E12: 0.0 | F12: 0.0 | G12: 0.0 | I12: =AND($E12="1.0", OR($F12="1.0",$G12="1.0")) -> FALSE | J12: =AND($F12="1.0", OR($E12="1.0",$G12="1.0")) -> FALSE | K12: =AND($G12="1.0", OR($F12="1.0",$E12="1.0")) -> FALSE
A13: 13 | B13: 3.3945399e+17 | C13: @bpkelly12 if that damn book lady decides to stop being a fuckin retard ill be out of here in 2 days | D13: 0 | E13: 0.0 | F13: 0.0 | G13: 0.0 | I13: =AND($E13="1.0", OR($F13="1.0",$G13="1.0")) -> FALSE | J13: =AND($F13="1.0", OR($E13="1.0",$G13="1.0")) -> FALSE | K13: =AND($G13="1.0", OR($F13="1.0",$E13="1.0")) -> FALSE
... A1141: 1260 | B1141: 1.3444853e+18 | C1141: @berriemoomin #런쥔을_공평하게_대하세요 Renjun deserve better treatment #Please_Treat_Renjun_Fairly please treat Renjun fairly | D1141: 0 | E1141: 0.0 | F1141: 0.0 | G1141: 0.0 | I1141: =AND($E1141="1.0", OR($F1141="1.0",$G1141="1.0")) -> FALSE | J1141: =AND($F1141="1.0", OR($E1141="1.0",$G1141="1.0")) -> FALSE | K1141: =AND($G1141="1.0", OR($F1141="1.0",$E1141="1.0")) -> FALSE

Sheet Indicateurs
B2: science_related | C2: scientific_claim | D2: scientific_reference | E2: scientific_context
A3: Nb | B3: =COUNTIFS(données!D$1:D$1142, "1") -> 375 | C3: =COUNTIFS(données!E$1:E$1142, "1.0") -> 263 | D3: =COUNTIFS(données!F$1:F$1142, "1.0") -> 203 | E3: =COUNTIFS(données!G$1:G$1142, "1.0") -> 251 | H3: reference + claim | I3: reference + context
A4: Nb chevauchant | B4: / | C4: =COUNTIFS(données!E$1:E$1142, "1.0",données!I$1:I$1142,TRUE) -> 139 | D4: =COUNTIFS(données!F$1:F$1142, "1.0",données!J$1:J$1142,TRUE) -> 203 | E4: =COUNTIFS(données!G$1:G$1142, "1.0",données!K$1:K$1142,TRUE) -> 218 | G4: Nb | H4: =COUNTIFS(données!E$1:E$1142, "1.0",données!F$1:F$1142, "1.0") -> 124 | I4: =COUNTIFS(données!G$1:G$1142, "1.0",données!F$1:F$1142, "1.0") -> 203
A5: Part des chevauchant | B5: / | C5: =C4/C3 -> 0.52851711 | D5: =D4/D3 -> 1 | E5: =E4/E3 -> 0.8685259 | G5: Part des scientific_reference | H5: =H4/$D$3 -> 0.61083744 | I5: =I4/$D$3 -> 1

Sheet prétraitements
B1: science_related | C1: scientific_claim | D1: scientific_reference | E1: scientific_context
A2: Ponctuation | B2: x | C2: x | D2: x | E2: x
A3: URL | B3: x | C3: x | D3: x | E3: x
A4: Mention utilisateur | C4: x | D4: x
A5: Emojis | D5: x
A6: #texte > HASHTAG + texte | C6: x | E6: x
A7: #texte > HASHTAG
A8: #texte > texte | B8: x | D8: x
A9: Occurrence minimale | B9: 3 | C9: 3 | D9: 3 | E9: 3
A10: Présence maximale | B10: 1 | C10: 0.8 | D10: 0.8 | E10: 0.8
A11: N grams | B11: 1 | C11: 1, 2 | D11: 1, 2 ,3 | E11: 1, 2
A13: Stratégie d'équilibrage | B13: SMOTE | C13: SMOTE | D13: copy | E13: None

Sheet features
A1: top | B1: science_related | D1: scientific_claim | E1: scientific_claim | F1: scientific_reference | H1: scientific_context
B2: Features | C2: Score | D2: Features | E2: Score | F2: Features | G2: Score | H2: Features | I2: Score
A3: 1 | B3: stop | C3: 59.633642 | D3: USER | E3: 2.2979694 | F3: url | G3: 1.9845687 | H3: url | I3: 0.26483211
A4: 2 | B4: support | C4: 35.591322 | D4: url | E4: 2.170765 | F4: increase | G4: 1.1354649 | H4: increase | I4: 0.064980698
A5: 3 | B5: url | C5: 35.410478 | D5: look | E5: 1.8749172 | F5: eurekamag | G5: 1.0920498 | H5: lead | I5: 0.038255549
A6: 4 | B6: health | C6: 30.916696 | D6: medical | E6: 1.7494155 | F6: support | G6: 1.0073674 | H6: stop | I6: 0.037786087
A7: 5 | B7: study | C7: 28.468602 | D7: late | E7: 1.7423057 | F7: url USER | G7: 0.85469713 | H7: study | I7: 0.0377036
A8: 6 | B8: risk | C8: 21.978857 | D8: increase | E8: 1.7381477 | F8: stop | G8: 0.82365825 | H8: help | I8: 0.023086431
A9: 7 | B9: research | C9: 15.764846 | D9: science url | E9: 1.680248 | F9: scientist | G9: 0.81343807 | H9: research | I9: 0.022893677
A10: 8 | B10: reduce | C10: 15.344718 | D10: hashtag_eurekamag | E10: 1.518355 | F10: brain | G10: 0.80011495 | H10: cause | I10: 0.02184384
A11: 9 | B11: virus | C11: 15.098813 | D11: scientist | E11: 1.4791034 | F11: study | G11: 0.77336121 | H11: url url | I11: 0.021725443
A12: 10 | B12: science | C12: 13.405282 | D12: stem | E12: 1.4408552 | F12: find | G12: 0.75654861 | H12: science | I12: 0.018970115
A13: 11 | B13: cancer | C13: 13.247386 | D13: site | E13: 1.4161017 | F13: lead | G13: 0.73377529 | H13: problem | I13: 0.018352529
A14: 12 | B14: therapy | C14: 13.11251 | D14: post | E14: 1.3780005 | F14: new | G14: 0.71996539 | H14: death | I14: 0.017874228
... A22: 20 | B22: article | C22: 10.026138 | D22: associate | E22: 1.2610379 | F22: think | G22: 0.50704331 | H22: good | I22: 0.0088875069
